st_on_hover_tabs_ven/__init__.py
st_on_hover_tabs_ven/frontend/build/asset-manifest.json
st_on_hover_tabs_ven/frontend/build/bootstrap.min.css
st_on_hover_tabs_ven/frontend/build/index.html
st_on_hover_tabs_ven/frontend/build/precache-manifest.7b61fec73fa49d87d9e787826c4b4a7c.js
st_on_hover_tabs_ven/frontend/build/service-worker.js
st_on_hover_tabs_ven/frontend/build/static/css/2.0a4cb73c.chunk.css
st_on_hover_tabs_ven/frontend/build/static/css/2.0a4cb73c.chunk.css.map
st_on_hover_tabs_ven/frontend/build/static/css/main.db61388b.chunk.css
st_on_hover_tabs_ven/frontend/build/static/css/main.db61388b.chunk.css.map
st_on_hover_tabs_ven/frontend/build/static/js/2.f1e083b5.chunk.js
st_on_hover_tabs_ven/frontend/build/static/js/2.f1e083b5.chunk.js.LICENSE.txt
st_on_hover_tabs_ven/frontend/build/static/js/2.f1e083b5.chunk.js.map
st_on_hover_tabs_ven/frontend/build/static/js/main.65f94142.chunk.js
st_on_hover_tabs_ven/frontend/build/static/js/main.65f94142.chunk.js.map
st_on_hover_tabs_ven/frontend/build/static/js/runtime-main.11ec9aca.js
st_on_hover_tabs_ven/frontend/build/static/js/runtime-main.11ec9aca.js.map
st_on_progress/__init__.py
st_on_progress/frontend/build/asset-manifest.json
st_on_progress/frontend/build/bootstrap.min.css
st_on_progress/frontend/build/index.html
st_on_progress/frontend/build/precache-manifest.bd3eb54add71fdaeffe74d116e69cbea.js
st_on_progress/frontend/build/service-worker.js
st_on_progress/frontend/build/static/css/main.239f2e9a.chunk.css
st_on_progress/frontend/build/static/css/main.239f2e9a.chunk.css.map
st_on_progress/frontend/build/static/js/2.15acec80.chunk.js
st_on_progress/frontend/build/static/js/2.15acec80.chunk.js.LICENSE.txt
st_on_progress/frontend/build/static/js/2.15acec80.chunk.js.map
st_on_progress/frontend/build/static/js/main.0ee0b23e.chunk.js
st_on_progress/frontend/build/static/js/main.0ee0b23e.chunk.js.map
st_on_progress/frontend/build/static/js/runtime-main.11ec9aca.js
streamlit_on_progress-0.0.3.dist-info/LICENSE
streamlit_on_progress-0.0.3.dist-info/METADATA
streamlit_on_progress-0.0.3.dist-info/WHEEL
streamlit_on_progress-0.0.3.dist-info/top_level.txt
streamlit_on_progress-0.0.3.dist-info/RECORD
